spoe_forge/__init__.py
spoe_forge/agent/__init__.py
spoe_forge/agent/context.py
spoe_forge/agent/exceptions.py
spoe_forge/agent/registry.py
spoe_forge/cli.py
spoe_forge/exception.py
spoe_forge/log.py
spoe_forge/server/__init__.py
spoe_forge/server/configuration.py
spoe_forge/server/constants.py
spoe_forge/server/handler.py
spoe_forge/spoe_forge.py
spoe_forge/spop/__init__.py
spoe_forge/spop/constants.py
spoe_forge/spop/decoders/__init__.py
spoe_forge/spop/decoders/data_types.py
spoe_forge/spop/decoders/payloads.py
spoe_forge/spop/encoders/__init__.py
spoe_forge/spop/encoders/data_types.py
spoe_forge/spop/encoders/payloads.py
spoe_forge/spop/exception.py
spoe_forge/spop/frame.py
spoe_forge/spop/spop_types.py
spoe_forge-0.0.3.dist-info/WHEEL
spoe_forge-0.0.3.dist-info/entry_points.txt
spoe_forge-0.0.3.dist-info/METADATA
spoe_forge-0.0.3.dist-info/RECORD
