Metadata-Version: 2.3
Name: spoe-forge
Version: 0.0.3
Summary: A pure Python framework for building HAProxy SPOE agents
Keywords: haproxy,spoe,spoa,spop
Author: Mike O'Donnell
Author-email: Mike O'Donnell <mike@devferret.com>
License: MIT
Classifier: Development Status :: 5 - Production/Stable
Classifier: Intended Audience :: Developers
Classifier: License :: OSI Approved :: MIT License
Classifier: Programming Language :: Python :: 3
Classifier: Programming Language :: Python :: 3.12
Requires-Dist: pre-commit>=4.1.0 ; extra == 'dev'
Requires-Dist: ruff==0.14.2 ; extra == 'dev'
Requires-Dist: pytest==9.0.1 ; extra == 'test'
Requires-Dist: pytest-asyncio==1.3.0 ; extra == 'test'
Requires-Dist: coveralls==4.0.2 ; extra == 'test'
Requires-Dist: coverage==7.13.0 ; extra == 'test'
Requires-Dist: pytest-cov==7.0.0 ; extra == 'test'
Requires-Python: >=3.12
Project-URL: Homepage, https://github.com/mwodonnell/spoe-forge
Project-URL: Repository, https://github.com/mwodonnell/spoe-forge
Provides-Extra: dev
Provides-Extra: test
